pybacktestchain_ss/__init__.py
pybacktestchain_ss/backtests/AmberHorseTailor.csv
pybacktestchain_ss/backtests/AmberTigerEngineer.csv
pybacktestchain_ss/backtests/BlackEagleSoldier.csv
pybacktestchain_ss/backtests/BlackFoxEngineer.csv
pybacktestchain_ss/backtests/BlackJaguarFarmer.csv
pybacktestchain_ss/backtests/BlackLeopardNurse.csv
pybacktestchain_ss/backtests/BlackLionMechanic.csv
pybacktestchain_ss/backtests/BlackLynxPlumber.csv
pybacktestchain_ss/backtests/BlueFalconAstronaut.csv
pybacktestchain_ss/backtests/BlueHawkArtist.csv
pybacktestchain_ss/backtests/BlueHorseMechanic.csv
pybacktestchain_ss/backtests/BluePantherDoctor.csv
pybacktestchain_ss/backtests/BlueWolfSoldier.csv
pybacktestchain_ss/backtests/BrownCheetahDoctor.csv
pybacktestchain_ss/backtests/BrownEagleArchitect.csv
pybacktestchain_ss/backtests/BrownTigerFirefighter.csv
pybacktestchain_ss/backtests/CrimsonGorillaLawyer.csv
pybacktestchain_ss/backtests/GoldCheetahMechanic.csv
pybacktestchain_ss/backtests/GoldGorillaArchitect.csv
pybacktestchain_ss/backtests/GreenEagleBlacksmith.csv
pybacktestchain_ss/backtests/GreyHawkChef.csv
pybacktestchain_ss/backtests/GreyJaguarArchitect.csv
pybacktestchain_ss/backtests/GreyLeopardMechanic.csv
pybacktestchain_ss/backtests/GreyLionPilot.csv
pybacktestchain_ss/backtests/IndigoBearPilot.csv
pybacktestchain_ss/backtests/IndigoCobraEngineer.csv
pybacktestchain_ss/backtests/IndigoSharkArchitect.csv
pybacktestchain_ss/backtests/MagentaCheetahDoctor.csv
pybacktestchain_ss/backtests/MagentaFoxMechanic.csv
pybacktestchain_ss/backtests/MagentaHorseBlacksmith.csv
pybacktestchain_ss/backtests/MagentaLionChef.csv
pybacktestchain_ss/backtests/MagentaPantherDoctor.csv
pybacktestchain_ss/backtests/MagentaSharkPilot.csv
pybacktestchain_ss/backtests/OrangeCobraChef.csv
pybacktestchain_ss/backtests/OrangeFalconMechanic.csv
pybacktestchain_ss/backtests/PinkLionMechanic.csv
pybacktestchain_ss/backtests/PinkTigerPlumber.csv
pybacktestchain_ss/backtests/PurpleCobraLawyer.csv
pybacktestchain_ss-0.10.9.dist-info/LICENSE
pybacktestchain_ss-0.10.9.dist-info/METADATA
pybacktestchain_ss-0.10.9.dist-info/WHEEL
pybacktestchain_ss-0.10.9.dist-info/RECORD
