Metadata-Version: 2.3
Name: pybacktestchain_ss
Version: 0.10.9
Summary: Enchancing the pybacktestchain package. Made by Samuli Salonen as the individual assignment for the M203 Python course.
License: MIT
Author: Samuli Salonen
Requires-Python: >=3.11,<4.0
Classifier: License :: OSI Approved :: MIT License
Classifier: Programming Language :: Python :: 3
Classifier: Programming Language :: Python :: 3.11
Classifier: Programming Language :: Python :: 3.12
Classifier: Programming Language :: Python :: 3.13
Requires-Dist: matplotlib (>=3.10.0,<4.0.0)
Requires-Dist: numba (>=0.60.0,<0.61.0)
Requires-Dist: numpy (>=1.22,<2.1)
Requires-Dist: pybacktestchain (>=0.2.1,<0.3.0)
Requires-Dist: scipy (<1.14.0)
Requires-Dist: sec-cik-mapper (>=2.1.0,<3.0.0)
Requires-Dist: yfinance (>=0.2.51,<0.3.0)
